[
  {
    "epoch": 1,
    "train_loss": 2.271975310338943,
    "val_loss": 2.0777209005701662,
    "val_cer": 0.8343259653869904,
    "val_wer": 1.0963336533547545,
    "val_eos_rate": 1.0,
    "val_forced_eos_rate": 0.24479166666666666,
    "val_global_max_rate": 0.0,
    "val_avg_pred_len": 109.30729166666667,
    "val_avg_ref_len": 133.97916666666666,
    "val_pred_ref_len_ratio": 0.8158529000155498,
    "val_avg_max_char_run": 1.0,
    "val_avg_repeated_bigram_rate": 0.0,
    "best_val_loss": 2.0777209005701662,
    "seconds": 546.7730958461761
  },
  {
    "epoch": 2,
    "train_loss": 2.0498156628465543,
    "val_loss": 1.954089464171777,
    "val_cer": 0.7630233889178163,
    "val_wer": 1.046973462632707,
    "val_eos_rate": 1.0,
    "val_forced_eos_rate": 0.13541666666666666,
    "val_global_max_rate": 0.0,
    "val_avg_pred_len": 103.39583333333333,
    "val_avg_ref_len": 133.97916666666666,
    "val_pred_ref_len_ratio": 0.7717306795210699,
    "val_avg_max_char_run": 1.0,
    "val_avg_repeated_bigram_rate": 0.0,
    "best_val_loss": 1.954089464171777,
    "seconds": 647.5470840930939
  },
  {
    "epoch": 3,
    "train_loss": 1.9537736240098489,
    "val_loss": 1.851876725072586,
    "val_cer": 0.7411636169686234,
    "val_wer": 1.0649935172583755,
    "val_eos_rate": 1.0,
    "val_forced_eos_rate": 0.11458333333333333,
    "val_global_max_rate": 0.0,
    "val_avg_pred_len": 106.484375,
    "val_avg_ref_len": 133.97916666666666,
    "val_pred_ref_len_ratio": 0.7947830819468201,
    "val_avg_max_char_run": 1.0,
    "val_avg_repeated_bigram_rate": 0.0,
    "best_val_loss": 1.851876725072586,
    "seconds": 583.6359407901764
  },
  {
    "epoch": 4,
    "train_loss": 1.8570229683855293,
    "val_loss": 1.7130589989284961,
    "val_cer": 0.7094371012006929,
    "val_wer": 1.0235130482691204,
    "val_eos_rate": 1.0,
    "val_forced_eos_rate": 0.09895833333333333,
    "val_global_max_rate": 0.0,
    "val_avg_pred_len": 108.67708333333333,
    "val_avg_ref_len": 133.97916666666666,
    "val_pred_ref_len_ratio": 0.8111491214430104,
    "val_avg_max_char_run": 1.1510416666666667,
    "val_avg_repeated_bigram_rate": 0.0038665370873158613,
    "best_val_loss": 1.7130589989284961,
    "seconds": 586.9470767974854
  },
  {
    "epoch": 5,
    "train_loss": 1.750752858055177,
    "val_loss": 1.5978194315133256,
    "val_cer": 0.6663885205884497,
    "val_wer": 1.042288729015233,
    "val_eos_rate": 1.0,
    "val_forced_eos_rate": 0.09375,
    "val_global_max_rate": 0.0,
    "val_avg_pred_len": 113.84895833333333,
    "val_avg_ref_len": 133.97916666666666,
    "val_pred_ref_len_ratio": 0.8497512051002954,
    "val_avg_max_char_run": 1.0,
    "val_avg_repeated_bigram_rate": 0.0,
    "best_val_loss": 1.5978194315133256,
    "seconds": 584.1555790901184
  },
  {
    "epoch": 6,
    "train_loss": 1.6671299156707782,
    "val_loss": 1.5085063060502817,
    "val_cer": 0.6347275647794631,
    "val_wer": 1.0549065228689223,
    "val_eos_rate": 1.0,
    "val_forced_eos_rate": 0.11458333333333333,
    "val_global_max_rate": 0.0,
    "val_avg_pred_len": 115.88020833333333,
    "val_avg_ref_len": 133.97916666666666,
    "val_pred_ref_len_ratio": 0.8649121443010419,
    "val_avg_max_char_run": 1.0104166666666667,
    "val_avg_repeated_bigram_rate": 0.0,
    "best_val_loss": 1.5085063060502817,
    "seconds": 491.01097226142883
  },
  {
    "epoch": 7,
    "train_loss": 1.594903459472214,
    "val_loss": 1.4262100782496228,
    "val_cer": 0.613705387718893,
    "val_wer": 0.9669902997049801,
    "val_eos_rate": 1.0,
    "val_forced_eos_rate": 0.078125,
    "val_global_max_rate": 0.0,
    "val_avg_pred_len": 115.20833333333333,
    "val_avg_ref_len": 133.97916666666666,
    "val_pred_ref_len_ratio": 0.8598973721038718,
    "val_avg_max_char_run": 1.1197916666666667,
    "val_avg_repeated_bigram_rate": 0.0006012273655882862,
    "best_val_loss": 1.4262100782496228,
    "seconds": 483.2718939781189
  },
  {
    "epoch": 8,
    "train_loss": 1.5347420221928454,
    "val_loss": 1.3542794718727604,
    "val_cer": 0.5944866967990764,
    "val_wer": 0.948360586373349,
    "val_eos_rate": 1.0,
    "val_forced_eos_rate": 0.08333333333333333,
    "val_global_max_rate": 0.0,
    "val_avg_pred_len": 113.95833333333333,
    "val_avg_ref_len": 133.97916666666666,
    "val_pred_ref_len_ratio": 0.8505675633649511,
    "val_avg_max_char_run": 1.046875,
    "val_avg_repeated_bigram_rate": 0.00021385945591999525,
    "best_val_loss": 1.3542794718727604,
    "seconds": 484.229816198349
  }
]